Metadata-Version: 2.4
Name: adafruit-circuitpython-ble-file-transfer
Version: 4.0.12
Summary: Simple BLE Service for reading and writing files over BLE
Author-email: Adafruit Industries <circuitpython@adafruit.com>
License: MIT
Project-URL: Homepage, https://github.com/adafruit/Adafruit_CircuitPython_BLE_File_Transfer.git
Keywords: adafruit,blinka,circuitpython,micropython,ble_file_transfer,ble,file,transfer
Classifier: Intended Audience :: Developers
Classifier: Topic :: Software Development :: Libraries
Classifier: Topic :: Software Development :: Embedded Systems
Classifier: Topic :: System :: Hardware
Classifier: License :: OSI Approved :: MIT License
Classifier: Programming Language :: Python :: 3
License-File: LICENSE
Requires-Dist: Adafruit-Blinka
Requires-Dist: adafruit-circuitpython-ble
Provides-Extra: optional
Dynamic: license-file
